soniox/__init__.py
soniox/capture_device.py
soniox/conversion.py
soniox/manage_speakers.py
soniox/manage_speech_contexts.py
soniox/multi_channel_utils.py
soniox/speech_service.py
soniox/speech_service_pb2.py
soniox/speech_service_pb2_grpc.py
soniox/transcribe_file.py
soniox/transcribe_live.py
soniox_test-1.4.0.dist-info/LICENSE
soniox_test-1.4.0.dist-info/METADATA
soniox_test-1.4.0.dist-info/WHEEL
soniox_test-1.4.0.dist-info/top_level.txt
soniox_test-1.4.0.dist-info/RECORD
