Metadata-Version: 2.1
Name: soniox-test
Version: 1.4.0
Summary: Soniox speech recognition service client library
Home-page: https://soniox.com/
Author: Soniox Inc
Author-email: support@soniox.com
Classifier: Programming Language :: Python :: 3
Classifier: License :: OSI Approved :: MIT License
Classifier: Operating System :: OS Independent
Requires-Python: >=3.6
License-File: LICENSE
Requires-Dist: grpcio
Requires-Dist: protobuf
Requires-Dist: numpy
Requires-Dist: SoundCard
